LICENSE.txt
MANIFEST.in
README.md
README.rst
privacy
setup.cfg
setup.py
buddysuite/AlignBuddy.py
buddysuite/BuddySuite.py
buddysuite/DatabaseBuddy.py
buddysuite/PhyloBuddy.py
buddysuite/SeqBuddy.py
buddysuite/__init__.py
buddysuite/buddy_resources.py
buddysuite.egg-info/PKG-INFO
buddysuite.egg-info/SOURCES.txt
buddysuite.egg-info/dependency_links.txt
buddysuite.egg-info/entry_points.txt
buddysuite.egg-info/not-zip-safe
buddysuite.egg-info/requires.txt
buddysuite.egg-info/top_level.txt