Metadata-Version: 1.1
Name: buddysuite
Version: 1.3.0
Summary: BuddySuite is a collection of command line utilities written in Python for working with biological data.
Home-page: https://github.com/biologyguy/BuddySuite
Author: Stephen Bond
Author-email: steve.bond@gmail.com
License: Public Domain
Keywords: computational biology,computational genetics,genetics,genome,phylogenetics,biology,bioinformatics
Platform: UNKNOWN
Classifier: Development Status :: 5 - Production/Stable
Classifier: Topic :: Scientific/Engineering
Classifier: Topic :: Scientific/Engineering :: Bio-Informatics
Classifier: Topic :: Software Development :: Libraries :: Python Modules
Classifier: Intended Audience :: Science/Research
Classifier: Operating System :: MacOS :: MacOS X
Classifier: Operating System :: POSIX :: Linux
Classifier: Operating System :: Microsoft :: Windows
Classifier: Programming Language :: Python :: 3
Classifier: Programming Language :: Python :: 3.4
Classifier: Programming Language :: Python :: 3.5
Classifier: Programming Language :: Python :: 3 :: Only
Classifier: License :: Public Domain
Classifier: Natural Language :: English
Classifier: Environment :: Console
